{
  "generatedAt": "2026-05-19T05:24:27.215Z",
  "readOnly": true,
  "classificationRules": [
    "EXPECTED_SINGLE: one active Team record for one public school inside one ageGroup/gender/league/season context.",
    "EXPECTED_MULTI_CONTEXT: same public school has teams across different age groups, genders, leagues, or seasons.",
    "DUPLICATE_SAME_CONTEXT: more than one active Team record maps to the same public school inside the same ageGroup/gender/league/season context.",
    "INACTIVE_OR_UNCLEAR: active Team record has no active official game context. List separately; do not merge automatically."
  ],
  "summary": {
    "activeTeamsInspected": 36,
    "activeOfficialGamesInspected": 91,
    "contextGroups": 20,
    "expectedSingleGroups": 20,
    "expectedMultiContextSchoolGroups": 8,
    "duplicateSameContextGroups": 0,
    "inactiveOrUnclearTeams": 19,
    "affectedGames": 0,
    "affectedGameStats": 0,
    "repairedU16TeamsWouldBeTouched": false,
    "repairedU19DlszTeamsWouldBeTouched": false,
    "ratingsRecomputationNeeded": false
  },
  "duplicateSameContextGroups": [],
  "proposedDuplicateRepairs": [],
  "expectedMultiContextGroups": [
    {
      "classification": "EXPECTED_MULTI_CONTEXT",
      "publicSchoolDisplayName": "Adamson University",
      "contexts": [
        {
          "ageGroup": "U16",
          "gender": "Boys",
          "leagueId": "c112c09d-75ac-46ed-96e4-ce2852bfba75",
          "leagueName": "UAAP Season 88 16U Boys Basketball",
          "seasonId": "39a4a46c-6362-411f-ae85-6f631414f30b",
          "seasonName": "Season 88",
          "internalTeamNames": [
            "ADU U16 Boys"
          ]
        },
        {
          "ageGroup": "U19",
          "gender": "Boys",
          "leagueId": "d721a82a-f182-4a54-983a-01453650ec9e",
          "leagueName": "UAAP Season 88 HS Boys Basketball",
          "seasonId": "77858fdc-9a0b-4b4a-8820-4ad0a105a8a9",
          "seasonName": "Season 88",
          "internalTeamNames": [
            "ADU"
          ]
        }
      ]
    },
    {
      "classification": "EXPECTED_MULTI_CONTEXT",
      "publicSchoolDisplayName": "Ateneo de Manila University",
      "contexts": [
        {
          "ageGroup": "U16",
          "gender": "Boys",
          "leagueId": "c112c09d-75ac-46ed-96e4-ce2852bfba75",
          "leagueName": "UAAP Season 88 16U Boys Basketball",
          "seasonId": "39a4a46c-6362-411f-ae85-6f631414f30b",
          "seasonName": "Season 88",
          "internalTeamNames": [
            "ATENEO U16 Boys"
          ]
        },
        {
          "ageGroup": "U19",
          "gender": "Boys",
          "leagueId": "d721a82a-f182-4a54-983a-01453650ec9e",
          "leagueName": "UAAP Season 88 HS Boys Basketball",
          "seasonId": "77858fdc-9a0b-4b4a-8820-4ad0a105a8a9",
          "seasonName": "Season 88",
          "internalTeamNames": [
            "ATENEO"
          ]
        },
        {
          "ageGroup": "U19",
          "gender": "Girls",
          "leagueId": "ea377aba-7d8a-48b9-acb1-0ecaa1e12aef",
          "leagueName": "UAAP Season 88 HS Girls Basketball",
          "seasonId": "308c354b-3f3e-418e-ba34-5d6f7de9485e",
          "seasonName": "Season 88",
          "internalTeamNames": [
            "ATENEO"
          ]
        }
      ]
    },
    {
      "classification": "EXPECTED_MULTI_CONTEXT",
      "publicSchoolDisplayName": "De La Salle Santiago Zobel",
      "contexts": [
        {
          "ageGroup": "U16",
          "gender": "Boys",
          "leagueId": "c112c09d-75ac-46ed-96e4-ce2852bfba75",
          "leagueName": "UAAP Season 88 16U Boys Basketball",
          "seasonId": "39a4a46c-6362-411f-ae85-6f631414f30b",
          "seasonName": "Season 88",
          "internalTeamNames": [
            "DLSZ U16 Boys"
          ]
        },
        {
          "ageGroup": "U19",
          "gender": "Boys",
          "leagueId": "d721a82a-f182-4a54-983a-01453650ec9e",
          "leagueName": "UAAP Season 88 HS Boys Basketball",
          "seasonId": "77858fdc-9a0b-4b4a-8820-4ad0a105a8a9",
          "seasonName": "Season 88",
          "internalTeamNames": [
            "DLSZ U19 Boys"
          ]
        },
        {
          "ageGroup": "U19",
          "gender": "Girls",
          "leagueId": "ea377aba-7d8a-48b9-acb1-0ecaa1e12aef",
          "leagueName": "UAAP Season 88 HS Girls Basketball",
          "seasonId": "308c354b-3f3e-418e-ba34-5d6f7de9485e",
          "seasonName": "Season 88",
          "internalTeamNames": [
            "DLSZ U19 Girls"
          ]
        }
      ]
    },
    {
      "classification": "EXPECTED_MULTI_CONTEXT",
      "publicSchoolDisplayName": "Far Eastern University",
      "contexts": [
        {
          "ageGroup": "U16",
          "gender": "Boys",
          "leagueId": "c112c09d-75ac-46ed-96e4-ce2852bfba75",
          "leagueName": "UAAP Season 88 16U Boys Basketball",
          "seasonId": "39a4a46c-6362-411f-ae85-6f631414f30b",
          "seasonName": "Season 88",
          "internalTeamNames": [
            "FEU U16 Boys"
          ]
        },
        {
          "ageGroup": "U19",
          "gender": "Boys",
          "leagueId": "d721a82a-f182-4a54-983a-01453650ec9e",
          "leagueName": "UAAP Season 88 HS Boys Basketball",
          "seasonId": "77858fdc-9a0b-4b4a-8820-4ad0a105a8a9",
          "seasonName": "Season 88",
          "internalTeamNames": [
            "FEU"
          ]
        }
      ]
    },
    {
      "classification": "EXPECTED_MULTI_CONTEXT",
      "publicSchoolDisplayName": "National University Nazareth School",
      "contexts": [
        {
          "ageGroup": "U16",
          "gender": "Boys",
          "leagueId": "c112c09d-75ac-46ed-96e4-ce2852bfba75",
          "leagueName": "UAAP Season 88 16U Boys Basketball",
          "seasonId": "39a4a46c-6362-411f-ae85-6f631414f30b",
          "seasonName": "Season 88",
          "internalTeamNames": [
            "NU U16 Boys"
          ]
        },
        {
          "ageGroup": "U19",
          "gender": "Boys",
          "leagueId": "d721a82a-f182-4a54-983a-01453650ec9e",
          "leagueName": "UAAP Season 88 HS Boys Basketball",
          "seasonId": "77858fdc-9a0b-4b4a-8820-4ad0a105a8a9",
          "seasonName": "Season 88",
          "internalTeamNames": [
            "NU"
          ]
        },
        {
          "ageGroup": "U19",
          "gender": "Girls",
          "leagueId": "ea377aba-7d8a-48b9-acb1-0ecaa1e12aef",
          "leagueName": "UAAP Season 88 HS Girls Basketball",
          "seasonId": "308c354b-3f3e-418e-ba34-5d6f7de9485e",
          "seasonName": "Season 88",
          "internalTeamNames": [
            "NU"
          ]
        }
      ]
    },
    {
      "classification": "EXPECTED_MULTI_CONTEXT",
      "publicSchoolDisplayName": "University of Santo Tomas",
      "contexts": [
        {
          "ageGroup": "U16",
          "gender": "Boys",
          "leagueId": "c112c09d-75ac-46ed-96e4-ce2852bfba75",
          "leagueName": "UAAP Season 88 16U Boys Basketball",
          "seasonId": "39a4a46c-6362-411f-ae85-6f631414f30b",
          "seasonName": "Season 88",
          "internalTeamNames": [
            "UST U16 Boys"
          ]
        },
        {
          "ageGroup": "U19",
          "gender": "Boys",
          "leagueId": "d721a82a-f182-4a54-983a-01453650ec9e",
          "leagueName": "UAAP Season 88 HS Boys Basketball",
          "seasonId": "77858fdc-9a0b-4b4a-8820-4ad0a105a8a9",
          "seasonName": "Season 88",
          "internalTeamNames": [
            "UST"
          ]
        },
        {
          "ageGroup": "U19",
          "gender": "Girls",
          "leagueId": "ea377aba-7d8a-48b9-acb1-0ecaa1e12aef",
          "leagueName": "UAAP Season 88 HS Girls Basketball",
          "seasonId": "308c354b-3f3e-418e-ba34-5d6f7de9485e",
          "seasonName": "Season 88",
          "internalTeamNames": [
            "UST"
          ]
        }
      ]
    },
    {
      "classification": "EXPECTED_MULTI_CONTEXT",
      "publicSchoolDisplayName": "University of the East",
      "contexts": [
        {
          "ageGroup": "U16",
          "gender": "Boys",
          "leagueId": "c112c09d-75ac-46ed-96e4-ce2852bfba75",
          "leagueName": "UAAP Season 88 16U Boys Basketball",
          "seasonId": "39a4a46c-6362-411f-ae85-6f631414f30b",
          "seasonName": "Season 88",
          "internalTeamNames": [
            "UE U16 Boys"
          ]
        },
        {
          "ageGroup": "U19",
          "gender": "Boys",
          "leagueId": "d721a82a-f182-4a54-983a-01453650ec9e",
          "leagueName": "UAAP Season 88 HS Boys Basketball",
          "seasonId": "77858fdc-9a0b-4b4a-8820-4ad0a105a8a9",
          "seasonName": "Season 88",
          "internalTeamNames": [
            "UE"
          ]
        }
      ]
    },
    {
      "classification": "EXPECTED_MULTI_CONTEXT",
      "publicSchoolDisplayName": "University of the Philippines Integrated School",
      "contexts": [
        {
          "ageGroup": "U16",
          "gender": "Boys",
          "leagueId": "c112c09d-75ac-46ed-96e4-ce2852bfba75",
          "leagueName": "UAAP Season 88 16U Boys Basketball",
          "seasonId": "39a4a46c-6362-411f-ae85-6f631414f30b",
          "seasonName": "Season 88",
          "internalTeamNames": [
            "UP U16 Boys"
          ]
        },
        {
          "ageGroup": "U19",
          "gender": "Boys",
          "leagueId": "d721a82a-f182-4a54-983a-01453650ec9e",
          "leagueName": "UAAP Season 88 HS Boys Basketball",
          "seasonId": "77858fdc-9a0b-4b4a-8820-4ad0a105a8a9",
          "seasonName": "Season 88",
          "internalTeamNames": [
            "UP"
          ]
        }
      ]
    }
  ],
  "inactiveOrUnclear": [
    {
      "classification": "INACTIVE_OR_UNCLEAR",
      "teamId": "e9b2dc44-3103-4612-ab7a-5ce67e7ef6a8",
      "teamName": "ADU Jrs (ADU)",
      "publicSchoolDisplayName": "Adamson University",
      "city": "Quezon City",
      "region": "NCR",
      "reason": "No active official games found for this Team record. Do not merge automatically without historical/archive review."
    },
    {
      "classification": "INACTIVE_OR_UNCLEAR",
      "teamId": "acb69a9e-e10c-4486-b3e1-9fe8c056c57c",
      "teamName": "ATENEO Girls (ATENEO)",
      "publicSchoolDisplayName": "Ateneo de Manila University",
      "city": "Quezon City",
      "region": "NCR",
      "reason": "No active official games found for this Team record. Do not merge automatically without historical/archive review."
    },
    {
      "classification": "INACTIVE_OR_UNCLEAR",
      "teamId": "1f44864b-91c6-4b52-a1d3-1b88eee3b487",
      "teamName": "ATENEO JRS (ATENEO)",
      "publicSchoolDisplayName": "Ateneo de Manila University",
      "city": "Quezon City",
      "region": "NCR",
      "reason": "No active official games found for this Team record. Do not merge automatically without historical/archive review."
    },
    {
      "classification": "INACTIVE_OR_UNCLEAR",
      "teamId": "4108ff02-d59f-41aa-9219-070d56cfa5bc",
      "teamName": "DE LA SALLE Jrs (DLSU)",
      "publicSchoolDisplayName": "De La Salle Santiago Zobel",
      "city": "Quezon City",
      "region": "NCR",
      "reason": "No active official games found for this Team record. Do not merge automatically without historical/archive review."
    },
    {
      "classification": "INACTIVE_OR_UNCLEAR",
      "teamId": "5bad0e3c-bdf8-46b4-9d62-32be7ca9b1ee",
      "teamName": "De La Salle Santiago Zobel",
      "publicSchoolDisplayName": "De La Salle Santiago Zobel",
      "city": "Metro Manila",
      "region": "NCR",
      "reason": "No active official games found for this Team record. Do not merge automatically without historical/archive review."
    },
    {
      "classification": "INACTIVE_OR_UNCLEAR",
      "teamId": "ae091b25-12cd-453f-af06-b629247174c9",
      "teamName": "DLSU",
      "publicSchoolDisplayName": "De La Salle Santiago Zobel",
      "city": "Metro Manila",
      "region": "NCR",
      "reason": "No active official games found for this Team record. Do not merge automatically without historical/archive review."
    },
    {
      "classification": "INACTIVE_OR_UNCLEAR",
      "teamId": "ffd348d4-fd53-47c8-92b5-06beecd3a6de",
      "teamName": "DLSZ",
      "publicSchoolDisplayName": "De La Salle Santiago Zobel",
      "city": "Metro Manila",
      "region": "NCR",
      "reason": "No active official games found for this Team record. Do not merge automatically without historical/archive review."
    },
    {
      "classification": "INACTIVE_OR_UNCLEAR",
      "teamId": "99d138ba-9679-4f6b-adfa-ace87d9125b4",
      "teamName": "LA SALLE",
      "publicSchoolDisplayName": "De La Salle Santiago Zobel",
      "city": "Metro Manila",
      "region": "NCR",
      "reason": "No active official games found for this Team record. Do not merge automatically without historical/archive review."
    },
    {
      "classification": "INACTIVE_OR_UNCLEAR",
      "teamId": "53650e64-ec1e-48cd-b2eb-5f575362e691",
      "teamName": "LA SALLE (DLSZ)",
      "publicSchoolDisplayName": "De La Salle Santiago Zobel",
      "city": "San Juan",
      "region": "NCR",
      "reason": "No active official games found for this Team record. Do not merge automatically without historical/archive review."
    },
    {
      "classification": "INACTIVE_OR_UNCLEAR",
      "teamId": "c010e83f-8a2d-4084-8497-0bea7119c6db",
      "teamName": "LA SALLE Girls (DLSU)",
      "publicSchoolDisplayName": "De La Salle Santiago Zobel",
      "city": "San Juan",
      "region": "NCR",
      "reason": "No active official games found for this Team record. Do not merge automatically without historical/archive review."
    },
    {
      "classification": "INACTIVE_OR_UNCLEAR",
      "teamId": "8b25947c-21d2-4878-a44f-32dc5160b5bd",
      "teamName": "LA SALLE Girls (LA SALLE)",
      "publicSchoolDisplayName": "De La Salle Santiago Zobel",
      "city": "San Juan",
      "region": "NCR",
      "reason": "No active official games found for this Team record. Do not merge automatically without historical/archive review."
    },
    {
      "classification": "INACTIVE_OR_UNCLEAR",
      "teamId": "8f999ac0-0823-4eac-91af-842957c026ff",
      "teamName": "LA SALLE Jrs (LA SALLE)",
      "publicSchoolDisplayName": "De La Salle Santiago Zobel",
      "city": "Quezon City",
      "region": "NCR",
      "reason": "No active official games found for this Team record. Do not merge automatically without historical/archive review."
    },
    {
      "classification": "INACTIVE_OR_UNCLEAR",
      "teamId": "b9efc141-ef1a-4214-aebf-3a9db0f2071d",
      "teamName": "FEU Jrs (FEU)",
      "publicSchoolDisplayName": "Far Eastern University",
      "city": "Manila",
      "region": "NCR",
      "reason": "No active official games found for this Team record. Do not merge automatically without historical/archive review."
    },
    {
      "classification": "INACTIVE_OR_UNCLEAR",
      "teamId": "9ebec3dc-2e89-4a32-9326-54297c71f8bc",
      "teamName": "NU Girls (NU)",
      "publicSchoolDisplayName": "National University Nazareth School",
      "city": "Quezon City",
      "region": "NCR",
      "reason": "No active official games found for this Team record. Do not merge automatically without historical/archive review."
    },
    {
      "classification": "INACTIVE_OR_UNCLEAR",
      "teamId": "d81d5179-b450-4eba-b7a2-07f558a9268c",
      "teamName": "NU Jrs (NU)",
      "publicSchoolDisplayName": "National University Nazareth School",
      "city": "Quezon City",
      "region": "NCR",
      "reason": "No active official games found for this Team record. Do not merge automatically without historical/archive review."
    },
    {
      "classification": "INACTIVE_OR_UNCLEAR",
      "teamId": "8d66d8b4-c047-4257-b3b7-3d87b1a09aa3",
      "teamName": "UST Girls (UST)",
      "publicSchoolDisplayName": "University of Santo Tomas",
      "city": "San Juan",
      "region": "NCR",
      "reason": "No active official games found for this Team record. Do not merge automatically without historical/archive review."
    },
    {
      "classification": "INACTIVE_OR_UNCLEAR",
      "teamId": "7c2934ce-f07a-4f5c-af9e-d3d291b7428c",
      "teamName": "UST Jrs (UST)",
      "publicSchoolDisplayName": "University of Santo Tomas",
      "city": "Quezon City",
      "region": "NCR",
      "reason": "No active official games found for this Team record. Do not merge automatically without historical/archive review."
    },
    {
      "classification": "INACTIVE_OR_UNCLEAR",
      "teamId": "e560fa7d-c846-465b-98b4-7704cb17416b",
      "teamName": "UE Jrs (UE)",
      "publicSchoolDisplayName": "University of the East",
      "city": "Manila",
      "region": "NCR",
      "reason": "No active official games found for this Team record. Do not merge automatically without historical/archive review."
    },
    {
      "classification": "INACTIVE_OR_UNCLEAR",
      "teamId": "e8e50710-0e6a-4482-ae1d-452b3471fdde",
      "teamName": "UPIS Jrs (UP)",
      "publicSchoolDisplayName": "University of the Philippines Integrated School",
      "city": "Quezon City",
      "region": "NCR",
      "reason": "No active official games found for this Team record. Do not merge automatically without historical/archive review."
    }
  ],
  "aliasChecks": [
    {
      "alias": "ADU",
      "teams": [
        {
          "teamId": "28eaa2c2-be45-4de6-a030-acf090e0069c",
          "teamName": "ADU",
          "publicSchoolDisplayName": "Adamson University",
          "activeContextCount": 1
        },
        {
          "teamId": "e9b2dc44-3103-4612-ab7a-5ce67e7ef6a8",
          "teamName": "ADU Jrs (ADU)",
          "publicSchoolDisplayName": "Adamson University",
          "activeContextCount": 0
        },
        {
          "teamId": "685e9651-ad77-4824-b70c-f032365e1f80",
          "teamName": "ADU U16 Boys",
          "publicSchoolDisplayName": "Adamson University",
          "activeContextCount": 1
        }
      ],
      "duplicateSameContextGroups": []
    },
    {
      "alias": "ATENEO",
      "teams": [
        {
          "teamId": "a1d6a2b9-f100-4677-bbd4-853254e9de91",
          "teamName": "ATENEO",
          "publicSchoolDisplayName": "Ateneo de Manila University",
          "activeContextCount": 2
        },
        {
          "teamId": "acb69a9e-e10c-4486-b3e1-9fe8c056c57c",
          "teamName": "ATENEO Girls (ATENEO)",
          "publicSchoolDisplayName": "Ateneo de Manila University",
          "activeContextCount": 0
        },
        {
          "teamId": "1f44864b-91c6-4b52-a1d3-1b88eee3b487",
          "teamName": "ATENEO JRS (ATENEO)",
          "publicSchoolDisplayName": "Ateneo de Manila University",
          "activeContextCount": 0
        },
        {
          "teamId": "f7afb1a1-b2ec-4a7f-a72e-d668d39d2661",
          "teamName": "ATENEO U16 Boys",
          "publicSchoolDisplayName": "Ateneo de Manila University",
          "activeContextCount": 1
        }
      ],
      "duplicateSameContextGroups": []
    },
    {
      "alias": "DLSU",
      "teams": [
        {
          "teamId": "4108ff02-d59f-41aa-9219-070d56cfa5bc",
          "teamName": "DE LA SALLE Jrs (DLSU)",
          "publicSchoolDisplayName": "De La Salle Santiago Zobel",
          "activeContextCount": 0
        },
        {
          "teamId": "ae091b25-12cd-453f-af06-b629247174c9",
          "teamName": "DLSU",
          "publicSchoolDisplayName": "De La Salle Santiago Zobel",
          "activeContextCount": 0
        },
        {
          "teamId": "c010e83f-8a2d-4084-8497-0bea7119c6db",
          "teamName": "LA SALLE Girls (DLSU)",
          "publicSchoolDisplayName": "De La Salle Santiago Zobel",
          "activeContextCount": 0
        }
      ],
      "duplicateSameContextGroups": []
    },
    {
      "alias": "DLSZ",
      "teams": [
        {
          "teamId": "ffd348d4-fd53-47c8-92b5-06beecd3a6de",
          "teamName": "DLSZ",
          "publicSchoolDisplayName": "De La Salle Santiago Zobel",
          "activeContextCount": 0
        },
        {
          "teamId": "3739a9f4-21ef-4938-83ff-811433a47656",
          "teamName": "DLSZ U16 Boys",
          "publicSchoolDisplayName": "De La Salle Santiago Zobel",
          "activeContextCount": 1
        },
        {
          "teamId": "f5480f4e-456e-427c-b2f2-6802f94b7470",
          "teamName": "DLSZ U19 Boys",
          "publicSchoolDisplayName": "De La Salle Santiago Zobel",
          "activeContextCount": 1
        },
        {
          "teamId": "564ae4ca-61d1-496e-9472-ee3819df8ce6",
          "teamName": "DLSZ U19 Girls",
          "publicSchoolDisplayName": "De La Salle Santiago Zobel",
          "activeContextCount": 1
        },
        {
          "teamId": "53650e64-ec1e-48cd-b2eb-5f575362e691",
          "teamName": "LA SALLE (DLSZ)",
          "publicSchoolDisplayName": "De La Salle Santiago Zobel",
          "activeContextCount": 0
        }
      ],
      "duplicateSameContextGroups": []
    },
    {
      "alias": "LA SALLE",
      "teams": [
        {
          "teamId": "4108ff02-d59f-41aa-9219-070d56cfa5bc",
          "teamName": "DE LA SALLE Jrs (DLSU)",
          "publicSchoolDisplayName": "De La Salle Santiago Zobel",
          "activeContextCount": 0
        },
        {
          "teamId": "5bad0e3c-bdf8-46b4-9d62-32be7ca9b1ee",
          "teamName": "De La Salle Santiago Zobel",
          "publicSchoolDisplayName": "De La Salle Santiago Zobel",
          "activeContextCount": 0
        },
        {
          "teamId": "ae091b25-12cd-453f-af06-b629247174c9",
          "teamName": "DLSU",
          "publicSchoolDisplayName": "De La Salle Santiago Zobel",
          "activeContextCount": 0
        },
        {
          "teamId": "ffd348d4-fd53-47c8-92b5-06beecd3a6de",
          "teamName": "DLSZ",
          "publicSchoolDisplayName": "De La Salle Santiago Zobel",
          "activeContextCount": 0
        },
        {
          "teamId": "3739a9f4-21ef-4938-83ff-811433a47656",
          "teamName": "DLSZ U16 Boys",
          "publicSchoolDisplayName": "De La Salle Santiago Zobel",
          "activeContextCount": 1
        },
        {
          "teamId": "f5480f4e-456e-427c-b2f2-6802f94b7470",
          "teamName": "DLSZ U19 Boys",
          "publicSchoolDisplayName": "De La Salle Santiago Zobel",
          "activeContextCount": 1
        },
        {
          "teamId": "564ae4ca-61d1-496e-9472-ee3819df8ce6",
          "teamName": "DLSZ U19 Girls",
          "publicSchoolDisplayName": "De La Salle Santiago Zobel",
          "activeContextCount": 1
        },
        {
          "teamId": "99d138ba-9679-4f6b-adfa-ace87d9125b4",
          "teamName": "LA SALLE",
          "publicSchoolDisplayName": "De La Salle Santiago Zobel",
          "activeContextCount": 0
        },
        {
          "teamId": "53650e64-ec1e-48cd-b2eb-5f575362e691",
          "teamName": "LA SALLE (DLSZ)",
          "publicSchoolDisplayName": "De La Salle Santiago Zobel",
          "activeContextCount": 0
        },
        {
          "teamId": "c010e83f-8a2d-4084-8497-0bea7119c6db",
          "teamName": "LA SALLE Girls (DLSU)",
          "publicSchoolDisplayName": "De La Salle Santiago Zobel",
          "activeContextCount": 0
        },
        {
          "teamId": "8b25947c-21d2-4878-a44f-32dc5160b5bd",
          "teamName": "LA SALLE Girls (LA SALLE)",
          "publicSchoolDisplayName": "De La Salle Santiago Zobel",
          "activeContextCount": 0
        },
        {
          "teamId": "8f999ac0-0823-4eac-91af-842957c026ff",
          "teamName": "LA SALLE Jrs (LA SALLE)",
          "publicSchoolDisplayName": "De La Salle Santiago Zobel",
          "activeContextCount": 0
        }
      ],
      "duplicateSameContextGroups": []
    },
    {
      "alias": "FEU",
      "teams": [
        {
          "teamId": "8f5d2b7d-e353-482f-8665-9f16e7c8290d",
          "teamName": "FEU",
          "publicSchoolDisplayName": "Far Eastern University",
          "activeContextCount": 1
        },
        {
          "teamId": "b9efc141-ef1a-4214-aebf-3a9db0f2071d",
          "teamName": "FEU Jrs (FEU)",
          "publicSchoolDisplayName": "Far Eastern University",
          "activeContextCount": 0
        },
        {
          "teamId": "604b7ecd-2cfe-4130-882e-28f7213a6240",
          "teamName": "FEU U16 Boys",
          "publicSchoolDisplayName": "Far Eastern University",
          "activeContextCount": 1
        }
      ],
      "duplicateSameContextGroups": []
    },
    {
      "alias": "NU",
      "teams": [
        {
          "teamId": "205e8c56-cac7-4823-b948-8aba9e8571f4",
          "teamName": "NU",
          "publicSchoolDisplayName": "National University Nazareth School",
          "activeContextCount": 2
        },
        {
          "teamId": "9ebec3dc-2e89-4a32-9326-54297c71f8bc",
          "teamName": "NU Girls (NU)",
          "publicSchoolDisplayName": "National University Nazareth School",
          "activeContextCount": 0
        },
        {
          "teamId": "d81d5179-b450-4eba-b7a2-07f558a9268c",
          "teamName": "NU Jrs (NU)",
          "publicSchoolDisplayName": "National University Nazareth School",
          "activeContextCount": 0
        },
        {
          "teamId": "179a4a3e-8dbd-4235-bae5-f0b5125bd0d7",
          "teamName": "NU U16 Boys",
          "publicSchoolDisplayName": "National University Nazareth School",
          "activeContextCount": 1
        }
      ],
      "duplicateSameContextGroups": []
    },
    {
      "alias": "NUNS",
      "teams": [],
      "duplicateSameContextGroups": []
    },
    {
      "alias": "UE",
      "teams": [
        {
          "teamId": "6e58e1c8-8684-4789-b4be-1ec0752b1057",
          "teamName": "UE",
          "publicSchoolDisplayName": "University of the East",
          "activeContextCount": 1
        },
        {
          "teamId": "e560fa7d-c846-465b-98b4-7704cb17416b",
          "teamName": "UE Jrs (UE)",
          "publicSchoolDisplayName": "University of the East",
          "activeContextCount": 0
        },
        {
          "teamId": "baa90e67-3f0a-49c7-8a4d-e10a1ff24ea3",
          "teamName": "UE U16 Boys",
          "publicSchoolDisplayName": "University of the East",
          "activeContextCount": 1
        }
      ],
      "duplicateSameContextGroups": []
    },
    {
      "alias": "UP",
      "teams": [
        {
          "teamId": "3e3baff4-9393-4cba-904f-c6aa0216d2a0",
          "teamName": "UP",
          "publicSchoolDisplayName": "University of the Philippines Integrated School",
          "activeContextCount": 1
        },
        {
          "teamId": "7f96dc7f-8690-4fa4-b87b-5497ba3d857b",
          "teamName": "UP U16 Boys",
          "publicSchoolDisplayName": "University of the Philippines Integrated School",
          "activeContextCount": 1
        },
        {
          "teamId": "e8e50710-0e6a-4482-ae1d-452b3471fdde",
          "teamName": "UPIS Jrs (UP)",
          "publicSchoolDisplayName": "University of the Philippines Integrated School",
          "activeContextCount": 0
        }
      ],
      "duplicateSameContextGroups": []
    },
    {
      "alias": "UPIS",
      "teams": [
        {
          "teamId": "e8e50710-0e6a-4482-ae1d-452b3471fdde",
          "teamName": "UPIS Jrs (UP)",
          "publicSchoolDisplayName": "University of the Philippines Integrated School",
          "activeContextCount": 0
        }
      ],
      "duplicateSameContextGroups": []
    },
    {
      "alias": "UST",
      "teams": [
        {
          "teamId": "16b51323-3fa8-4f62-8a5f-700fc418f7c5",
          "teamName": "UST",
          "publicSchoolDisplayName": "University of Santo Tomas",
          "activeContextCount": 2
        },
        {
          "teamId": "8d66d8b4-c047-4257-b3b7-3d87b1a09aa3",
          "teamName": "UST Girls (UST)",
          "publicSchoolDisplayName": "University of Santo Tomas",
          "activeContextCount": 0
        },
        {
          "teamId": "7c2934ce-f07a-4f5c-af9e-d3d291b7428c",
          "teamName": "UST Jrs (UST)",
          "publicSchoolDisplayName": "University of Santo Tomas",
          "activeContextCount": 0
        },
        {
          "teamId": "da58e619-1ed2-423f-8dac-b7e6c267a9f6",
          "teamName": "UST U16 Boys",
          "publicSchoolDisplayName": "University of Santo Tomas",
          "activeContextCount": 1
        }
      ],
      "duplicateSameContextGroups": []
    }
  ],
  "safetySummary": {
    "totalDuplicateGroups": 0,
    "totalAffectedGames": 0,
    "totalAffectedGameStats": 0,
    "anyU16RepairedTeamsWouldBeTouched": false,
    "anyU19RepairedDlszTeamsWouldBeTouched": false,
    "recommendedRepairOrder": [
      "Review all DUPLICATE_SAME_CONTEXT groups with high risk first.",
      "For each group, approve one canonical context-aware Team record or approve creation of a missing canonical Team.",
      "Repair one public school/context group per transaction.",
      "After each repair, validate active game counts, GameStats counts, point totals, and dynamic /teams standings.",
      "Leave INACTIVE_OR_UNCLEAR teams untouched until archived/test-data policy is confirmed."
    ]
  }
}
